CHANGELOG
LICENSE
MANIFEST.in
README.txt
ez_setup.py
setup.py
gasket/__init__.py
gasket/a.png
gasket/default.db
gasket/i.png
gasket/l.png
gasket/logo.svg
gasket/q.png
gasket/t.png
gasket/ui.glade
gasket.egg-info/PKG-INFO
gasket.egg-info/SOURCES.txt
gasket.egg-info/dependency_links.txt
gasket.egg-info/entry_points.txt
gasket.egg-info/not-zip-safe
gasket.egg-info/top_level.txt
