Metadata-Version: 1.0
Name: gasket
Version: 0.1
Summary: Simple note taking aplication for gnome
Home-page: http://joey101.net/gasket/
Author: Joey Marshall
Author-email: web@joey101.net
License: GPL
Keywords: gnome notes note simple
Platform: x11
